pyquota
