Metadata-Version: 2.1
Name: PyQuota
Version: 0.0.2
Summary: A simple python wrapper for C apis of quotactl
Home-page: https://github.com/tjumyk/pyquota
Author: tjumyk
Author-email: tjumyk@gmail.com
License: UNKNOWN
Platform: UNKNOWN
Classifier: Development Status :: 3 - Alpha
Classifier: Programming Language :: Python :: 3
Classifier: License :: OSI Approved :: MIT License
Classifier: Operating System :: POSIX :: Linux
